microvmi/__init__.py
microvmi/memory.py
microvmi/microvmi.py
microvmi/pymicrovmi.cpython-37m-x86_64-linux-gnu.so
microvmi/volatility/__init__.py
microvmi/volatility/vmi_handler.py
microvmi-0.2.13.dist-info/METADATA
microvmi-0.2.13.dist-info/WHEEL
microvmi-0.2.13.dist-info/top_level.txt
microvmi-0.2.13.dist-info/RECORD
