Metadata-Version: 2.1
Name: microvmi
Version: 0.2.13
Summary: Python bindings for libmicrovmi
Home-page: https://github.com/Wenzel/libmicrovmi
Author: Mathieu Tarral
Author-email: mathieu.tarral@protonmail.com
License: UNKNOWN
Platform: UNKNOWN
Classifier: Programming Language :: Python :: 3.6
Classifier: Development Status :: 4 - Beta
Classifier: License :: OSI Approved :: GNU General Public License v3 (GPLv3)
Requires-Python: >=3.6
Requires-Dist: setuptools-rust ==1.1.2
Requires-Dist: setuptools ==59.6.0
Requires-Dist: wheel
Requires-Dist: toml ==0.10.2
